imgup/__init__.py
imgup/cli.py
imgup-0.1.1.dist-info/METADATA
imgup-0.1.1.dist-info/WHEEL
imgup-0.1.1.dist-info/entry_points.txt
imgup-0.1.1.dist-info/top_level.txt
imgup-0.1.1.dist-info/RECORD
