Metadata-Version: 2.1
Name: imgup
Version: 0.1.1
Summary: A CLI tool to upload image to imgbb.com
Author: decryptable
Author-email: hello@decryptable.dev
Classifier: Programming Language :: Python :: 3
Classifier: License :: OSI Approved :: MIT License
Classifier: Operating System :: OS Independent
Requires-Python: >=3.6
Requires-Dist: requests
